aurigma/backoffice/__init__.py
aurigma/backoffice/api_client.py
aurigma/backoffice/api_response.py
aurigma/backoffice/configuration.py
aurigma/backoffice/exceptions.py
aurigma/backoffice/py.typed
aurigma/backoffice/rest.py
aurigma/backoffice/api/__init__.py
aurigma/backoffice/api/build_info_api.py
aurigma/backoffice/api/product_references_management_api.py
aurigma/backoffice/api/products_management_api.py
aurigma/backoffice/api/storefronts_management_api.py
aurigma/backoffice/api/users_management_api.py
aurigma/backoffice/models/__init__.py
aurigma/backoffice/models/appearance_data_dto.py
aurigma/backoffice/models/appearance_data_item_dto.py
aurigma/backoffice/models/appearance_data_type.py
aurigma/backoffice/models/big_commerce_settings_dto.py
aurigma/backoffice/models/big_commerce_storefront_dto.py
aurigma/backoffice/models/build_info_model.py
aurigma/backoffice/models/conflict_type.py
aurigma/backoffice/models/create_big_commerce_storefront_dto.py
aurigma/backoffice/models/create_custom_storefront_dto.py
aurigma/backoffice/models/create_magento_storefront_dto.py
aurigma/backoffice/models/create_nop_commerce_storefront_dto.py
aurigma/backoffice/models/create_product_design_connections_dto.py
aurigma/backoffice/models/create_product_document_connections_dto.py
aurigma/backoffice/models/create_product_dto.py
aurigma/backoffice/models/create_product_mockup_connections_dto.py
aurigma/backoffice/models/create_product_option_dto.py
aurigma/backoffice/models/create_product_option_value_dto.py
aurigma/backoffice/models/create_product_reference_dto.py
aurigma/backoffice/models/create_tenant_user_dto.py
aurigma/backoffice/models/create_woo_commerce_storefront_dto.py
aurigma/backoffice/models/custom_storefront_dto.py
aurigma/backoffice/models/general_conflict_dto.py
aurigma/backoffice/models/image_info.py
aurigma/backoffice/models/magento_settings_dto.py
aurigma/backoffice/models/magento_storefront_dto.py
aurigma_backoffice_api_client-1.0.0.dist-info/METADATA
aurigma_backoffice_api_client-1.0.0.dist-info/WHEEL
aurigma_backoffice_api_client-1.0.0.dist-info/top_level.txt
aurigma_backoffice_api_client-1.0.0.dist-info/RECORD
